kedro_local_notify/__init__.py
kedro_local_notify/hook.py
kedro_local_notify/static/kedro.png
kedro_local_notify-0.1.1.dist-info/entry_points.txt
kedro_local_notify-0.1.1.dist-info/LICENSE.md
kedro_local_notify-0.1.1.dist-info/WHEEL
kedro_local_notify-0.1.1.dist-info/METADATA
kedro_local_notify-0.1.1.dist-info/RECORD
